x_zic/__init__.py
x_zic/_version.py
x_zic/core/__init__.py
x_zic/core/config.py
x_zic/core/loader.py
x_zic/core/models.py
x_zic/data/tzdb-2025b/CONTRIBUTING
x_zic/data/tzdb-2025b/LICENSE
x_zic/data/tzdb-2025b/Makefile
x_zic/data/tzdb-2025b/NEWS
x_zic/data/tzdb-2025b/README
x_zic/data/tzdb-2025b/SECURITY
x_zic/data/tzdb-2025b/africa
x_zic/data/tzdb-2025b/antarctica
x_zic/data/tzdb-2025b/asctime.c
x_zic/data/tzdb-2025b/asia
x_zic/data/tzdb-2025b/australasia
x_zic/data/tzdb-2025b/backward
x_zic/data/tzdb-2025b/backzone
x_zic/data/tzdb-2025b/calendars
x_zic/data/tzdb-2025b/checklinks.awk
x_zic/data/tzdb-2025b/checknow.awk
x_zic/data/tzdb-2025b/checktab.awk
x_zic/data/tzdb-2025b/date.1
x_zic/data/tzdb-2025b/date.1.txt
x_zic/data/tzdb-2025b/date.c
x_zic/data/tzdb-2025b/difftime.c
x_zic/data/tzdb-2025b/etcetera
x_zic/data/tzdb-2025b/europe
x_zic/data/tzdb-2025b/factory
x_zic/data/tzdb-2025b/iso3166.tab
x_zic/data/tzdb-2025b/leap-seconds.list
x_zic/data/tzdb-2025b/leapseconds
x_zic/data/tzdb-2025b/leapseconds.awk
x_zic/data/tzdb-2025b/localtime.c
x_zic/data/tzdb-2025b/newctime.3
x_zic/data/tzdb-2025b/newctime.3.txt
x_zic/data/tzdb-2025b/newstrftime.3
x_zic/data/tzdb-2025b/newstrftime.3.txt
x_zic/data/tzdb-2025b/newtzset.3
x_zic/data/tzdb-2025b/newtzset.3.txt
x_zic/data/tzdb-2025b/northamerica
x_zic/data/tzdb-2025b/private.h
x_zic/data/tzdb-2025b/southamerica
x_zic/data/tzdb-2025b/strftime.c
x_zic/data/tzdb-2025b/theory.html
x_zic/data/tzdb-2025b/time2posix.3
x_zic/data/tzdb-2025b/time2posix.3.txt
x_zic/data/tzdb-2025b/to2050.tzs
x_zic/data/tzdb-2025b/tz-art.html
x_zic/data/tzdb-2025b/tz-how-to.html
x_zic/data/tzdb-2025b/tz-link.html
x_zic/data/tzdb-2025b/tzdata.zi
x_zic/data/tzdb-2025b/tzfile.5
x_zic/data/tzdb-2025b/tzfile.5.txt
x_zic/data/tzdb-2025b/tzfile.h
x_zic/data/tzdb-2025b/tzselect.8
x_zic/data/tzdb-2025b/tzselect.8.txt
x_zic/data/tzdb-2025b/tzselect.ksh
x_zic/data/tzdb-2025b/version
x_zic/data/tzdb-2025b/workman.sh
x_zic/data/tzdb-2025b/zdump.8
x_zic-0.2.0.dist-info/licenses/LICENSE
x_zic-0.2.0.dist-info/METADATA
x_zic-0.2.0.dist-info/WHEEL
x_zic-0.2.0.dist-info/top_level.txt
x_zic-0.2.0.dist-info/RECORD
