Metadata-Version: 2.4
Name: x-zic
Version: 0.2.0
Summary: Pythonic timezone compiler based on tzdb
Author-email: "m.lotfi" <m.lotfi@email.com>
Maintainer-email: "m.lotfi" <m.lotfi@email.com>
License:                     GNU GENERAL PUBLIC LICENSE
Project-URL: Homepage, https://github.com/mlotfic/x-zic
Project-URL: Documentation, https://x-zic.readthedocs.io
Project-URL: Repository, https://github.com/mlotfic/x-zic
Project-URL: Bug Tracker, https://github.com/mlotfic/x-zic/issues
Project-URL: Changelog, https://github.com/mlotfic/x-zic/blob/main/CHANGELOG.md
Project-URL: Source Code, https://github.com/mlotfic/x-zic
Project-URL: Download, https://pypi.org/project/x-zic/
Keywords: timezone,tzdb,iana,parser,dst,time
Classifier: Development Status :: 4 - Beta
Classifier: Intended Audience :: Developers
Classifier: License :: OSI Approved :: GNU General Public License v3 or later (GPLv3+)
Classifier: Operating System :: OS Independent
Classifier: Programming Language :: Python :: 3
Classifier: Programming Language :: Python :: 3.8
Classifier: Programming Language :: Python :: 3.9
Classifier: Programming Language :: Python :: 3.10
Classifier: Programming Language :: Python :: 3.11
Classifier: Programming Language :: Python :: 3.12
Classifier: Topic :: Software Development :: Libraries :: Python Modules
Classifier: Topic :: Software Development :: Libraries
Classifier: Topic :: Software Development :: Internationalization
Classifier: Topic :: Utilities
Requires-Python: >=3.8
License-File: LICENSE
Provides-Extra: pandas
Requires-Dist: pandas; extra == "pandas"
Provides-Extra: analysis
Requires-Dist: pandas; extra == "analysis"
Requires-Dist: numpy; extra == "analysis"
Provides-Extra: dev
Requires-Dist: pytest>=6.0; extra == "dev"
Requires-Dist: pytest-cov>=2.0; extra == "dev"
Requires-Dist: black>=22.0; extra == "dev"
Requires-Dist: flake8>=4.0; extra == "dev"
Requires-Dist: mypy>=0.900; extra == "dev"
Requires-Dist: pre-commit>=2.0; extra == "dev"
Requires-Dist: tox>=3.0; extra == "dev"
Requires-Dist: build>=0.10; extra == "dev"
Requires-Dist: twine>=4.0; extra == "dev"
Requires-Dist: setuptools_scm>=6.2; extra == "dev"
Requires-Dist: setuptools>=45; extra == "dev"
Requires-Dist: wheel; extra == "dev"
Requires-Dist: sphinx>=4.0; extra == "dev"
Requires-Dist: sphinx-rtd-theme>=1.0; extra == "dev"
Provides-Extra: test
Requires-Dist: pytest>=6.0; extra == "test"
Requires-Dist: pytest-cov>=2.0; extra == "test"
Requires-Dist: pytest-mock>=3.0; extra == "test"
Provides-Extra: docs
Requires-Dist: sphinx>=5.0; extra == "docs"
Requires-Dist: sphinx-rtd-theme>=1.0; extra == "docs"
Requires-Dist: myst-parser>=0.15; extra == "docs"
Requires-Dist: sphinx-copybutton>=0.3; extra == "docs"
Provides-Extra: lint
Requires-Dist: black>=22.0; extra == "lint"
Requires-Dist: flake8>=4.0; extra == "lint"
Requires-Dist: mypy>=0.900; extra == "lint"
Requires-Dist: isort>=5.0; extra == "lint"
Provides-Extra: all
Requires-Dist: pytest>=6.0; extra == "all"
Requires-Dist: pytest-cov>=2.0; extra == "all"
Requires-Dist: pytest-mock>=3.0; extra == "all"
Requires-Dist: black>=22.0; extra == "all"
Requires-Dist: flake8>=4.0; extra == "all"
Requires-Dist: mypy>=0.900; extra == "all"
Requires-Dist: isort>=5.0; extra == "all"
Requires-Dist: pre-commit>=2.0; extra == "all"
Requires-Dist: tox>=3.0; extra == "all"
Requires-Dist: build>=0.10; extra == "all"
Requires-Dist: twine>=4.0; extra == "all"
Requires-Dist: setuptools_scm>=6.2; extra == "all"
Requires-Dist: setuptools>=45; extra == "all"
Requires-Dist: wheel; extra == "all"
Requires-Dist: sphinx>=4.0; extra == "all"
Requires-Dist: sphinx-rtd-theme>=1.0; extra == "all"
Requires-Dist: myst-parser>=0.17.0; extra == "all"
Dynamic: license-file
